{"date":"1996-06-30","batting":[{"playerId":"mondr002","playerName":"Raúl Mondesí","gameId":"COL199606300","date":"1996-06-30T00:00:00.000Z","points":"49.00","stats":{"atBats":6,"hits":4,"doubles":0,"triples":1,"homeRuns":2,"runs":3,"rbi":6,"walks":0,"stolenBases":0,"hitByPitch":0}},{"playerId":"youne001","playerName":"Eric Young","gameId":"COL199606300","date":"1996-06-30T00:00:00.000Z","points":"46.00","stats":{"atBats":5,"hits":2,"doubles":0,"triples":0,"homeRuns":0,"runs":3,"rbi":1,"walks":1,"stolenBases":6,"hitByPitch":0}},{"playerId":"bichd001","playerName":"Dante Bichette","gameId":"COL199606300","date":"1996-06-30T00:00:00.000Z","points":"41.00","stats":{"atBats":6,"hits":5,"doubles":1,"triples":0,"homeRuns":1,"runs":2,"rbi":4,"walks":0,"stolenBases":1,"hitByPitch":0}},{"playerId":"burke001","playerName":"Ellis Burks","gameId":"COL199606300","date":"1996-06-30T00:00:00.000Z","points":"39.00","stats":{"atBats":4,"hits":3,"doubles":1,"triples":0,"homeRuns":1,"runs":3,"rbi":3,"walks":2,"stolenBases":1,"hitByPitch":0}},{"playerId":"jeffr001","playerName":"Reggie Jefferson","gameId":"BOS199606300","date":"1996-06-30T00:00:00.000Z","points":"35.00","stats":{"atBats":4,"hits":3,"doubles":0,"triples":0,"homeRuns":2,"runs":3,"rbi":3,"walks":0,"stolenBases":0,"hitByPitch":0}},{"playerId":"cangj001","playerName":"John Cangelosi","gameId":"HOU199606300","date":"1996-06-30T00:00:00.000Z","points":"33.00","stats":{"atBats":3,"hits":2,"doubles":0,"triples":0,"homeRuns":0,"runs":1,"rbi":3,"walks":2,"stolenBases":3,"hitByPitch":0}},{"playerId":"karre001","playerName":"Eric Karros","gameId":"COL199606300","date":"1996-06-30T00:00:00.000Z","points":"32.00","stats":{"atBats":5,"hits":2,"doubles":0,"triples":0,"homeRuns":2,"runs":3,"rbi":2,"walks":1,"stolenBases":0,"hitByPitch":0}},{"playerId":"camik001","playerName":"Ken Caminiti","gameId":"SFN199606300","date":"1996-06-30T00:00:00.000Z","points":"28.00","stats":{"atBats":4,"hits":3,"doubles":0,"triples":0,"homeRuns":1,"runs":2,"rbi":3,"walks":1,"stolenBases":0,"hitByPitch":0}},{"playerId":"nixoo001","playerName":"Otis Nixon","gameId":"TOR199606300","date":"1996-06-30T00:00:00.000Z","points":"25.00","stats":{"atBats":5,"hits":3,"doubles":0,"triples":0,"homeRuns":0,"runs":3,"rbi":0,"walks":0,"stolenBases":2,"hitByPitch":0}},{"playerId":"frymt001","playerName":"Travis Fryman","gameId":"BOS199606300","date":"1996-06-30T00:00:00.000Z","points":"24.00","stats":{"atBats":4,"hits":3,"doubles":1,"triples":0,"homeRuns":1,"runs":1,"rbi":2,"walks":0,"stolenBases":0,"hitByPitch":0}}],"pitching":[{"playerId":"kiled001","playerName":"Darryl Kile","gameId":"HOU199606300","date":"1996-06-30T00:00:00.000Z","points":"32.25","stats":{"inningsPitched":"9.0","hitsAllowed":6,"runsAllowed":3,"earnedRuns":3,"walks":2,"strikeouts":8,"hitBatters":0,"win":true,"loss":false,"save":false,"completeGame":true}},{"playerId":"welld001","playerName":"David Wells","gameId":"NYA199606300","date":"1996-06-30T00:00:00.000Z","points":"26.25","stats":{"inningsPitched":"9.0","hitsAllowed":4,"runsAllowed":1,"earnedRuns":1,"walks":1,"strikeouts":2,"hitBatters":1,"win":true,"loss":false,"save":false,"completeGame":true}},{"playerId":"mimbm001","playerName":"Michael Mimbs","gameId":"PHI199606300","date":"1996-06-30T00:00:00.000Z","points":"26.00","stats":{"inningsPitched":"8.0","hitsAllowed":3,"runsAllowed":2,"earnedRuns":1,"walks":1,"strikeouts":7,"hitBatters":0,"win":false,"loss":false,"save":false,"completeGame":false}},{"playerId":"hancr001","playerName":"Ryan Hancock","gameId":"CAL199606300","date":"1996-06-30T00:00:00.000Z","points":"25.75","stats":{"inningsPitched":"7.0","hitsAllowed":4,"runsAllowed":0,"earnedRuns":0,"walks":3,"strikeouts":6,"hitBatters":0,"win":true,"loss":false,"save":false,"completeGame":false}},{"playerId":"herso001","playerName":"Orel Hershiser","gameId":"CHA199606300","date":"1996-06-30T00:00:00.000Z","points":"23.00","stats":{"inningsPitched":"8.0","hitsAllowed":5,"runsAllowed":1,"earnedRuns":0,"walks":1,"strikeouts":3,"hitBatters":0,"win":true,"loss":false,"save":false,"completeGame":false}},{"playerId":"tracs001","playerName":"Steve Trachsel","gameId":"CIN199606300","date":"1996-06-30T00:00:00.000Z","points":"22.75","stats":{"inningsPitched":"7.0","hitsAllowed":4,"runsAllowed":0,"earnedRuns":0,"walks":2,"strikeouts":4,"hitBatters":0,"win":true,"loss":false,"save":false,"completeGame":false}},{"playerId":"rodrf001","playerName":"Frankie Rodriguez","gameId":"KCA199606300","date":"1996-06-30T00:00:00.000Z","points":"21.50","stats":{"inningsPitched":"7.1","hitsAllowed":5,"runsAllowed":2,"earnedRuns":2,"walks":1,"strikeouts":5,"hitBatters":0,"win":true,"loss":false,"save":false,"completeGame":false}},{"playerId":"wasdj001","playerName":"John Wasdin","gameId":"CAL199606300","date":"1996-06-30T00:00:00.000Z","points":"20.00","stats":{"inningsPitched":"8.0","hitsAllowed":4,"runsAllowed":1,"earnedRuns":1,"walks":2,"strikeouts":4,"hitBatters":1,"win":false,"loss":true,"save":false,"completeGame":true}},{"playerId":"stott001","playerName":"Todd Stottlemyre","gameId":"SLN199606300","date":"1996-06-30T00:00:00.000Z","points":"19.50","stats":{"inningsPitched":"6.0","hitsAllowed":4,"runsAllowed":1,"earnedRuns":1,"walks":1,"strikeouts":4,"hitBatters":0,"win":true,"loss":false,"save":false,"completeGame":false}},{"playerId":"hanse001","playerName":"Erik Hanson","gameId":"TOR199606300","date":"1996-06-30T00:00:00.000Z","points":"18.75","stats":{"inningsPitched":"7.0","hitsAllowed":5,"runsAllowed":2,"earnedRuns":2,"walks":1,"strikeouts":4,"hitBatters":0,"win":true,"loss":false,"save":false,"completeGame":false}}]}