{"date":"1911-05-14","batting":[{"playerId":"stovg101","playerName":"George Stovall","gameId":"CLE191105140","date":"1911-05-14T00:00:00.000Z","points":"22.00","stats":{"atBats":5,"hits":4,"doubles":0,"triples":0,"homeRuns":0,"runs":2,"rbi":3,"walks":0,"stolenBases":0,"hitByPitch":0}},{"playerId":"balln101","playerName":"Neal Ball","gameId":"CLE191105140","date":"1911-05-14T00:00:00.000Z","points":"21.00","stats":{"atBats":4,"hits":1,"doubles":0,"triples":1,"homeRuns":0,"runs":1,"rbi":2,"walks":1,"stolenBases":1,"hitByPitch":0}},{"playerId":"eastt101","playerName":"Ted Easterly","gameId":"CLE191105140","date":"1911-05-14T00:00:00.000Z","points":"21.00","stats":{"atBats":5,"hits":2,"doubles":0,"triples":1,"homeRuns":0,"runs":3,"rbi":2,"walks":0,"stolenBases":0,"hitByPitch":0}},{"playerId":"jackj101","playerName":"Shoeless Joe Jackson","gameId":"CLE191105140","date":"1911-05-14T00:00:00.000Z","points":"21.00","stats":{"atBats":5,"hits":2,"doubles":0,"triples":1,"homeRuns":0,"runs":2,"rbi":3,"walks":0,"stolenBases":0,"hitByPitch":0}},{"playerId":"bushd102","playerName":"Donie Bush","gameId":"DET191105140","date":"1911-05-14T00:00:00.000Z","points":"19.00","stats":{"atBats":3,"hits":2,"doubles":0,"triples":0,"homeRuns":0,"runs":2,"rbi":1,"walks":1,"stolenBases":1,"hitByPitch":0}},{"playerId":"garde101","playerName":"Earle Gardner","gameId":"CLE191105140","date":"1911-05-14T00:00:00.000Z","points":"18.00","stats":{"atBats":4,"hits":3,"doubles":0,"triples":0,"homeRuns":0,"runs":1,"rbi":1,"walks":0,"stolenBases":1,"hitByPitch":0}},{"playerId":"morig101","playerName":"George Moriarty","gameId":"DET191105140","date":"1911-05-14T00:00:00.000Z","points":"18.00","stats":{"atBats":4,"hits":3,"doubles":1,"triples":1,"homeRuns":0,"runs":1,"rbi":0,"walks":0,"stolenBases":0,"hitByPitch":0}},{"playerId":"olsoi101","playerName":"Ivy Olson","gameId":"CLE191105140","date":"1911-05-14T00:00:00.000Z","points":"17.00","stats":{"atBats":5,"hits":2,"doubles":0,"triples":1,"homeRuns":0,"runs":3,"rbi":0,"walks":0,"stolenBases":0,"hitByPitch":0}},{"playerId":"drakd101","playerName":"Delos Drake","gameId":"DET191105140","date":"1911-05-14T00:00:00.000Z","points":"17.00","stats":{"atBats":5,"hits":2,"doubles":0,"triples":1,"homeRuns":0,"runs":2,"rbi":1,"walks":0,"stolenBases":0,"hitByPitch":0}},{"playerId":"harks101","playerName":"Spec Harkness","gameId":"CLE191105140","date":"1911-05-14T00:00:00.000Z","points":"15.00","stats":{"atBats":5,"hits":3,"doubles":0,"triples":0,"homeRuns":0,"runs":1,"rbi":2,"walks":0,"stolenBases":0,"hitByPitch":0}}],"pitching":[{"playerId":"peltb101","playerName":"Barney Pelty","gameId":"SLA191105140","date":"1911-05-14T00:00:00.000Z","points":"26.25","stats":{"inningsPitched":"9.0","hitsAllowed":10,"runsAllowed":2,"earnedRuns":2,"walks":1,"strikeouts":6,"hitBatters":1,"win":true,"loss":false,"save":false,"completeGame":true}},{"playerId":"harks101","playerName":"Spec Harkness","gameId":"CLE191105140","date":"1911-05-14T00:00:00.000Z","points":"18.25","stats":{"inningsPitched":"9.0","hitsAllowed":11,"runsAllowed":3,"earnedRuns":1,"walks":1,"strikeouts":1,"hitBatters":0,"win":true,"loss":false,"save":false,"completeGame":true}},{"playerId":"livej101","playerName":"Jack Lively","gameId":"DET191105140","date":"1911-05-14T00:00:00.000Z","points":"13.50","stats":{"inningsPitched":"6.0","hitsAllowed":5,"runsAllowed":1,"earnedRuns":1,"walks":2,"strikeouts":2,"hitBatters":0,"win":true,"loss":false,"save":false,"completeGame":false}},{"playerId":"oteyb101","playerName":"Bill Otey","gameId":"SLA191105140","date":"1911-05-14T00:00:00.000Z","points":"12.50","stats":{"inningsPitched":"6.0","hitsAllowed":4,"runsAllowed":2,"earnedRuns":0,"walks":1,"strikeouts":2,"hitBatters":0,"win":false,"loss":false,"save":false,"completeGame":false}},{"playerId":"whitd104","playerName":"Doc White","gameId":"CHA191105140","date":"1911-05-14T00:00:00.000Z","points":"12.25","stats":{"inningsPitched":"9.0","hitsAllowed":10,"runsAllowed":5,"earnedRuns":3,"walks":3,"strikeouts":1,"hitBatters":1,"win":true,"loss":false,"save":false,"completeGame":true}},{"playerId":"collr103","playerName":"Ray Collins","gameId":"DET191105140","date":"1911-05-14T00:00:00.000Z","points":"4.00","stats":{"inningsPitched":"8.0","hitsAllowed":11,"runsAllowed":6,"earnedRuns":3,"walks":4,"strikeouts":2,"hitBatters":0,"win":false,"loss":true,"save":false,"completeGame":true}},{"playerId":"morgc102","playerName":"Cy Morgan","gameId":"CHA191105140","date":"1911-05-14T00:00:00.000Z","points":"1.50","stats":{"inningsPitched":"6.0","hitsAllowed":4,"runsAllowed":3,"earnedRuns":2,"walks":3,"strikeouts":1,"hitBatters":1,"win":false,"loss":true,"save":false,"completeGame":false}},{"playerId":"bendc101","playerName":"Charles Bender","gameId":"CHA191105140","date":"1911-05-14T00:00:00.000Z","points":"0.50","stats":{"inningsPitched":"2.0","hitsAllowed":4,"runsAllowed":3,"earnedRuns":0,"walks":0,"strikeouts":0,"hitBatters":0,"win":false,"loss":false,"save":false,"completeGame":false}},{"playerId":"quinj102","playerName":"Jack Quinn","gameId":"CLE191105140","date":"1911-05-14T00:00:00.000Z","points":"-6.00","stats":{"inningsPitched":"5.1","hitsAllowed":10,"runsAllowed":7,"earnedRuns":5,"walks":2,"strikeouts":2,"hitBatters":0,"win":false,"loss":false,"save":false,"completeGame":false}},{"playerId":"workr101","playerName":"Ralph Works","gameId":"DET191105140","date":"1911-05-14T00:00:00.000Z","points":"-11.25","stats":{"inningsPitched":"3.0","hitsAllowed":6,"runsAllowed":4,"earnedRuns":4,"walks":3,"strikeouts":0,"hitBatters":1,"win":false,"loss":false,"save":false,"completeGame":false}}]}