{"date":"1964-08-09","batting":[{"playerId":"maysw101","playerName":"Willie Mays","gameId":"CIN196408090","date":"1964-08-09T00:00:00.000Z","points":"41.00","stats":{"atBats":5,"hits":4,"doubles":1,"triples":0,"homeRuns":1,"runs":2,"rbi":3,"walks":0,"stolenBases":2,"hitByPitch":0}},{"playerId":"howsd101","playerName":"Dick Howser","gameId":"CLE196408091","date":"1964-08-09T00:00:00.000Z","points":"28.00","stats":{"atBats":4,"hits":2,"doubles":0,"triples":0,"homeRuns":1,"runs":2,"rbi":3,"walks":0,"stolenBases":1,"hitByPitch":0}},{"playerId":"mccow101","playerName":"Willie McCovey","gameId":"CIN196408090","date":"1964-08-09T00:00:00.000Z","points":"26.00","stats":{"atBats":5,"hits":3,"doubles":2,"triples":0,"homeRuns":1,"runs":1,"rbi":2,"walks":0,"stolenBases":0,"hitByPitch":0}},{"playerId":"robif103","playerName":"Frank Robinson","gameId":"CIN196408090","date":"1964-08-09T00:00:00.000Z","points":"26.00","stats":{"atBats":3,"hits":2,"doubles":0,"triples":0,"homeRuns":1,"runs":2,"rbi":2,"walks":0,"stolenBases":1,"hitByPitch":0}},{"playerId":"poweb101","playerName":"Boog Powell","gameId":"NYA196408092","date":"1964-08-09T00:00:00.000Z","points":"23.00","stats":{"atBats":4,"hits":2,"doubles":1,"triples":0,"homeRuns":1,"runs":2,"rbi":2,"walks":0,"stolenBases":0,"hitByPitch":0}},{"playerId":"mccat101","playerName":"Tim McCarver","gameId":"SLN196408090","date":"1964-08-09T00:00:00.000Z","points":"22.00","stats":{"atBats":3,"hits":3,"doubles":0,"triples":0,"homeRuns":0,"runs":1,"rbi":1,"walks":2,"stolenBases":1,"hitByPitch":0}},{"playerId":"kalia101","playerName":"Al Kaline","gameId":"DET196408092","date":"1964-08-09T00:00:00.000Z","points":"21.00","stats":{"atBats":3,"hits":2,"doubles":0,"triples":0,"homeRuns":1,"runs":1,"rbi":2,"walks":1,"stolenBases":0,"hitByPitch":0}},{"playerId":"kostf101","playerName":"Frank Kostro","gameId":"CLE196408092","date":"1964-08-09T00:00:00.000Z","points":"21.00","stats":{"atBats":4,"hits":2,"doubles":0,"triples":0,"homeRuns":1,"runs":1,"rbi":3,"walks":0,"stolenBases":0,"hitByPitch":0}},{"playerId":"stuad101","playerName":"Dick Stuart","gameId":"CHA196408091","date":"1964-08-09T00:00:00.000Z","points":"19.00","stats":{"atBats":4,"hits":2,"doubles":0,"triples":0,"homeRuns":1,"runs":1,"rbi":2,"walks":0,"stolenBases":0,"hitByPitch":0}},{"playerId":"thomf103","playerName":"Frank Thomas","gameId":"PHI196408090","date":"1964-08-09T00:00:00.000Z","points":"19.00","stats":{"atBats":4,"hits":2,"doubles":0,"triples":0,"homeRuns":1,"runs":1,"rbi":2,"walks":0,"stolenBases":0,"hitByPitch":0}}],"pitching":[{"playerId":"downa101","playerName":"Al Downing","gameId":"NYA196408091","date":"1964-08-09T00:00:00.000Z","points":"41.25","stats":{"inningsPitched":"9.0","hitsAllowed":4,"runsAllowed":1,"earnedRuns":1,"walks":1,"strikeouts":9,"hitBatters":0,"win":true,"loss":false,"save":false,"completeGame":true}},{"playerId":"bunnj101","playerName":"Jim Bunning","gameId":"PHI196408090","date":"1964-08-09T00:00:00.000Z","points":"37.25","stats":{"inningsPitched":"9.0","hitsAllowed":5,"runsAllowed":0,"earnedRuns":0,"walks":0,"strikeouts":6,"hitBatters":0,"win":true,"loss":false,"save":false,"completeGame":true}},{"playerId":"schwd101","playerName":"Don Schwall","gameId":"PIT196408090","date":"1964-08-09T00:00:00.000Z","points":"32.00","stats":{"inningsPitched":"8.0","hitsAllowed":3,"runsAllowed":0,"earnedRuns":0,"walks":2,"strikeouts":7,"hitBatters":0,"win":true,"loss":false,"save":false,"completeGame":false}},{"playerId":"kaatj101","playerName":"Jim Kaat","gameId":"CLE196408092","date":"1964-08-09T00:00:00.000Z","points":"29.25","stats":{"inningsPitched":"9.0","hitsAllowed":4,"runsAllowed":1,"earnedRuns":1,"walks":1,"strikeouts":3,"hitBatters":0,"win":true,"loss":false,"save":false,"completeGame":true}},{"playerId":"lemad102","playerName":"Denny Lemaster","gameId":"MLN196408090","date":"1964-08-09T00:00:00.000Z","points":"29.25","stats":{"inningsPitched":"9.0","hitsAllowed":4,"runsAllowed":2,"earnedRuns":2,"walks":3,"strikeouts":5,"hitBatters":0,"win":true,"loss":false,"save":false,"completeGame":true}},{"playerId":"siebs101","playerName":"Sonny Siebert","gameId":"CLE196408091","date":"1964-08-09T00:00:00.000Z","points":"26.25","stats":{"inningsPitched":"6.1","hitsAllowed":4,"runsAllowed":0,"earnedRuns":0,"walks":2,"strikeouts":7,"hitBatters":1,"win":true,"loss":false,"save":false,"completeGame":false}},{"playerId":"peteg101","playerName":"Gary Peters","gameId":"CHA196408092","date":"1964-08-09T00:00:00.000Z","points":"25.25","stats":{"inningsPitched":"9.0","hitsAllowed":6,"runsAllowed":1,"earnedRuns":1,"walks":5,"strikeouts":4,"hitBatters":0,"win":true,"loss":false,"save":false,"completeGame":true}},{"playerId":"sader101","playerName":"Ray Sadecki","gameId":"SLN196408090","date":"1964-08-09T00:00:00.000Z","points":"25.25","stats":{"inningsPitched":"9.0","hitsAllowed":7,"runsAllowed":2,"earnedRuns":2,"walks":2,"strikeouts":4,"hitBatters":0,"win":true,"loss":false,"save":false,"completeGame":true}},{"playerId":"odelb101","playerName":"Billy O'Dell","gameId":"CIN196408090","date":"1964-08-09T00:00:00.000Z","points":"21.00","stats":{"inningsPitched":"5.1","hitsAllowed":2,"runsAllowed":1,"earnedRuns":1,"walks":0,"strikeouts":4,"hitBatters":0,"win":true,"loss":false,"save":false,"completeGame":false}},{"playerId":"stafb101","playerName":"Bill Stafford","gameId":"NYA196408092","date":"1964-08-09T00:00:00.000Z","points":"19.00","stats":{"inningsPitched":"4.0","hitsAllowed":1,"runsAllowed":0,"earnedRuns":0,"walks":1,"strikeouts":6,"hitBatters":0,"win":false,"loss":false,"save":false,"completeGame":false}}]}