{"date":"1980-05-14","batting":[{"playerId":"skagd101","playerName":"Dave Skaggs","gameId":"CLE198005140","date":"1980-05-14T00:00:00.000Z","points":"32.00","stats":{"atBats":5,"hits":3,"doubles":0,"triples":0,"homeRuns":1,"runs":3,"rbi":5,"walks":0,"stolenBases":0,"hitByPitch":0}},{"playerId":"rosep001","playerName":"Pete Rose","gameId":"ATL198005140","date":"1980-05-14T00:00:00.000Z","points":"27.00","stats":{"atBats":4,"hits":3,"doubles":2,"triples":0,"homeRuns":0,"runs":2,"rbi":4,"walks":0,"stolenBases":0,"hitByPitch":1}},{"playerId":"trama001","playerName":"Alan Trammell","gameId":"DET198005140","date":"1980-05-14T00:00:00.000Z","points":"26.00","stats":{"atBats":4,"hits":4,"doubles":1,"triples":0,"homeRuns":0,"runs":3,"rbi":2,"walks":1,"stolenBases":0,"hitByPitch":0}},{"playerId":"ricej001","playerName":"Jim Rice","gameId":"BOS198005140","date":"1980-05-14T00:00:00.000Z","points":"25.00","stats":{"atBats":4,"hits":2,"doubles":0,"triples":0,"homeRuns":1,"runs":2,"rbi":4,"walks":0,"stolenBases":0,"hitByPitch":0}},{"playerId":"browb001","playerName":"Bobby Brown","gameId":"NYA198005140","date":"1980-05-14T00:00:00.000Z","points":"25.00","stats":{"atBats":4,"hits":2,"doubles":0,"triples":1,"homeRuns":0,"runs":4,"rbi":2,"walks":1,"stolenBases":0,"hitByPitch":0}},{"playerId":"hends001","playerName":"Steve Henderson","gameId":"CIN198005140","date":"1980-05-14T00:00:00.000Z","points":"24.00","stats":{"atBats":3,"hits":2,"doubles":0,"triples":1,"homeRuns":0,"runs":2,"rbi":0,"walks":2,"stolenBases":1,"hitByPitch":0}},{"playerId":"robed102","playerName":"Dave Roberts","gameId":"BAL198005140","date":"1980-05-14T00:00:00.000Z","points":"24.00","stats":{"atBats":3,"hits":1,"doubles":0,"triples":0,"homeRuns":1,"runs":1,"rbi":4,"walks":2,"stolenBases":0,"hitByPitch":0}},{"playerId":"randw001","playerName":"Willie Randolph","gameId":"NYA198005140","date":"1980-05-14T00:00:00.000Z","points":"24.00","stats":{"atBats":3,"hits":2,"doubles":2,"triples":0,"homeRuns":0,"runs":1,"rbi":3,"walks":3,"stolenBases":0,"hitByPitch":0}},{"playerId":"hortw101","playerName":"Willie Horton","gameId":"TOR198005140","date":"1980-05-14T00:00:00.000Z","points":"24.00","stats":{"atBats":4,"hits":3,"doubles":0,"triples":0,"homeRuns":1,"runs":2,"rbi":2,"walks":0,"stolenBases":0,"hitByPitch":0}},{"playerId":"sundj001","playerName":"Jim Sundberg","gameId":"BAL198005140","date":"1980-05-14T00:00:00.000Z","points":"23.00","stats":{"atBats":4,"hits":4,"doubles":1,"triples":0,"homeRuns":0,"runs":1,"rbi":0,"walks":1,"stolenBases":1,"hitByPitch":0}}],"pitching":[{"playerId":"abbog001","playerName":"Glenn Abbott","gameId":"TOR198005140","date":"1980-05-14T00:00:00.000Z","points":"33.25","stats":{"inningsPitched":"9.0","hitsAllowed":5,"runsAllowed":0,"earnedRuns":0,"walks":2,"strikeouts":5,"hitBatters":0,"win":true,"loss":false,"save":false,"completeGame":true}},{"playerId":"frymw101","playerName":"Woodie Fryman","gameId":"HOU198005140","date":"1980-05-14T00:00:00.000Z","points":"24.00","stats":{"inningsPitched":"4.0","hitsAllowed":0,"runsAllowed":0,"earnedRuns":0,"walks":0,"strikeouts":5,"hitBatters":0,"win":false,"loss":false,"save":true,"completeGame":false}},{"playerId":"carls001","playerName":"Steve Carlton","gameId":"ATL198005140","date":"1980-05-14T00:00:00.000Z","points":"19.50","stats":{"inningsPitched":"6.0","hitsAllowed":2,"runsAllowed":1,"earnedRuns":1,"walks":3,"strikeouts":4,"hitBatters":0,"win":true,"loss":false,"save":false,"completeGame":false}},{"playerId":"knepb001","playerName":"Bob Knepper","gameId":"SFN198005140","date":"1980-05-14T00:00:00.000Z","points":"18.75","stats":{"inningsPitched":"7.0","hitsAllowed":4,"runsAllowed":2,"earnedRuns":0,"walks":2,"strikeouts":6,"hitBatters":1,"win":false,"loss":true,"save":false,"completeGame":false}},{"playerId":"lucag001","playerName":"Gary Lucas","gameId":"SDN198005140","date":"1980-05-14T00:00:00.000Z","points":"18.00","stats":{"inningsPitched":"8.0","hitsAllowed":5,"runsAllowed":2,"earnedRuns":1,"walks":3,"strikeouts":6,"hitBatters":0,"win":false,"loss":true,"save":false,"completeGame":false}},{"playerId":"mcgll101","playerName":"Lynn McGlothen","gameId":"LAN198005140","date":"1980-05-14T00:00:00.000Z","points":"17.50","stats":{"inningsPitched":"6.0","hitsAllowed":2,"runsAllowed":1,"earnedRuns":1,"walks":1,"strikeouts":2,"hitBatters":0,"win":true,"loss":false,"save":false,"completeGame":false}},{"playerId":"sands001","playerName":"Scott Sanderson","gameId":"HOU198005140","date":"1980-05-14T00:00:00.000Z","points":"17.25","stats":{"inningsPitched":"5.0","hitsAllowed":4,"runsAllowed":0,"earnedRuns":0,"walks":3,"strikeouts":4,"hitBatters":0,"win":true,"loss":false,"save":false,"completeGame":false}},{"playerId":"bibbj001","playerName":"Jim Bibby","gameId":"SFN198005140","date":"1980-05-14T00:00:00.000Z","points":"15.75","stats":{"inningsPitched":"7.0","hitsAllowed":5,"runsAllowed":2,"earnedRuns":2,"walks":2,"strikeouts":3,"hitBatters":0,"win":true,"loss":false,"save":false,"completeGame":false}},{"playerId":"forsk001","playerName":"Ken Forsch","gameId":"HOU198005140","date":"1980-05-14T00:00:00.000Z","points":"15.00","stats":{"inningsPitched":"8.0","hitsAllowed":6,"runsAllowed":1,"earnedRuns":1,"walks":1,"strikeouts":4,"hitBatters":0,"win":false,"loss":true,"save":false,"completeGame":false}},{"playerId":"thomr001","playerName":"Roy Thomas","gameId":"SDN198005140","date":"1980-05-14T00:00:00.000Z","points":"14.75","stats":{"inningsPitched":"7.0","hitsAllowed":5,"runsAllowed":1,"earnedRuns":1,"walks":1,"strikeouts":1,"hitBatters":0,"win":true,"loss":false,"save":false,"completeGame":false}}]}