{"date":"2003-05-26","batting":[{"playerId":"felip001","playerName":"Pedro Feliz","gameId":"COL200305260","date":"2003-05-26T00:00:00.000Z","points":"30.00","stats":{"atBats":3,"hits":2,"doubles":0,"triples":1,"homeRuns":1,"runs":2,"rbi":2,"walks":2,"stolenBases":0,"hitByPitch":0}},{"playerId":"delld001","playerName":"David Dellucci","gameId":"ARI200305260","date":"2003-05-26T00:00:00.000Z","points":"28.00","stats":{"atBats":4,"hits":3,"doubles":1,"triples":0,"homeRuns":1,"runs":2,"rbi":2,"walks":0,"stolenBases":0,"hitByPitch":1}},{"playerId":"johnc002","playerName":"Charles Johnson","gameId":"COL200305260","date":"2003-05-26T00:00:00.000Z","points":"27.00","stats":{"atBats":3,"hits":2,"doubles":0,"triples":0,"homeRuns":1,"runs":2,"rbi":3,"walks":2,"stolenBases":0,"hitByPitch":0}},{"playerId":"yound001","playerName":"Dmitri Young","gameId":"DET200305260","date":"2003-05-26T00:00:00.000Z","points":"27.00","stats":{"atBats":3,"hits":2,"doubles":0,"triples":0,"homeRuns":1,"runs":1,"rbi":4,"walks":2,"stolenBases":0,"hitByPitch":0}},{"playerId":"woodc001","playerName":"Chris Woodward","gameId":"TOR200305260","date":"2003-05-26T00:00:00.000Z","points":"26.00","stats":{"atBats":4,"hits":3,"doubles":0,"triples":0,"homeRuns":1,"runs":3,"rbi":2,"walks":0,"stolenBases":0,"hitByPitch":0}},{"playerId":"wilsp002","playerName":"Preston Wilson","gameId":"COL200305260","date":"2003-05-26T00:00:00.000Z","points":"26.00","stats":{"atBats":5,"hits":3,"doubles":0,"triples":0,"homeRuns":1,"runs":2,"rbi":3,"walks":0,"stolenBases":0,"hitByPitch":0}},{"playerId":"guilj001","playerName":"José Guillén","gameId":"ATL200305260","date":"2003-05-26T00:00:00.000Z","points":"24.00","stats":{"atBats":6,"hits":3,"doubles":1,"triples":0,"homeRuns":1,"runs":1,"rbi":2,"walks":0,"stolenBases":0,"hitByPitch":0}},{"playerId":"berkl001","playerName":"Lance Berkman","gameId":"SLN200305260","date":"2003-05-26T00:00:00.000Z","points":"23.00","stats":{"atBats":5,"hits":2,"doubles":0,"triples":0,"homeRuns":1,"runs":2,"rbi":3,"walks":0,"stolenBases":0,"hitByPitch":0}},{"playerId":"jimed001","playerName":"D'Angelo Jimenez","gameId":"TOR200305260","date":"2003-05-26T00:00:00.000Z","points":"23.00","stats":{"atBats":4,"hits":2,"doubles":0,"triples":0,"homeRuns":1,"runs":2,"rbi":2,"walks":1,"stolenBases":0,"hitByPitch":0}},{"playerId":"encaj001","playerName":"Juan Encarnación","gameId":"FLO200305260","date":"2003-05-26T00:00:00.000Z","points":"23.00","stats":{"atBats":4,"hits":2,"doubles":1,"triples":0,"homeRuns":1,"runs":2,"rbi":2,"walks":0,"stolenBases":0,"hitByPitch":0}}],"pitching":[{"playerId":"pavac001","playerName":"Carl Pavano","gameId":"FLO200305260","date":"2003-05-26T00:00:00.000Z","points":"33.25","stats":{"inningsPitched":"9.0","hitsAllowed":5,"runsAllowed":1,"earnedRuns":1,"walks":0,"strikeouts":5,"hitBatters":0,"win":true,"loss":false,"save":false,"completeGame":true}},{"playerId":"woodk002","playerName":"Kerry Wood","gameId":"CHN200305260","date":"2003-05-26T00:00:00.000Z","points":"25.75","stats":{"inningsPitched":"7.0","hitsAllowed":1,"runsAllowed":1,"earnedRuns":1,"walks":4,"strikeouts":10,"hitBatters":1,"win":false,"loss":true,"save":false,"completeGame":false}},{"playerId":"foggj001","playerName":"Josh Fogg","gameId":"CHN200305260","date":"2003-05-26T00:00:00.000Z","points":"24.75","stats":{"inningsPitched":"7.0","hitsAllowed":3,"runsAllowed":0,"earnedRuns":0,"walks":3,"strikeouts":5,"hitBatters":0,"win":true,"loss":false,"save":false,"completeGame":false}},{"playerId":"gooda001","playerName":"Andrew Good","gameId":"ARI200305260","date":"2003-05-26T00:00:00.000Z","points":"22.75","stats":{"inningsPitched":"7.0","hitsAllowed":6,"runsAllowed":3,"earnedRuns":3,"walks":0,"strikeouts":7,"hitBatters":0,"win":true,"loss":false,"save":false,"completeGame":false}},{"playerId":"bondj001","playerName":"Jeremy Bonderman","gameId":"DET200305260","date":"2003-05-26T00:00:00.000Z","points":"19.50","stats":{"inningsPitched":"6.0","hitsAllowed":3,"runsAllowed":2,"earnedRuns":2,"walks":1,"strikeouts":7,"hitBatters":0,"win":false,"loss":false,"save":false,"completeGame":false}},{"playerId":"willw001","playerName":"Woody Williams","gameId":"SLN200305260","date":"2003-05-26T00:00:00.000Z","points":"18.50","stats":{"inningsPitched":"6.0","hitsAllowed":6,"runsAllowed":1,"earnedRuns":1,"walks":0,"strikeouts":5,"hitBatters":2,"win":true,"loss":false,"save":false,"completeGame":false}},{"playerId":"hampm001","playerName":"Mike Hampton","gameId":"ATL200305260","date":"2003-05-26T00:00:00.000Z","points":"17.50","stats":{"inningsPitched":"6.0","hitsAllowed":6,"runsAllowed":3,"earnedRuns":3,"walks":2,"strikeouts":9,"hitBatters":0,"win":false,"loss":false,"save":false,"completeGame":false}},{"playerId":"riedj001","playerName":"John Riedling","gameId":"ATL200305260","date":"2003-05-26T00:00:00.000Z","points":"16.00","stats":{"inningsPitched":"6.2","hitsAllowed":5,"runsAllowed":0,"earnedRuns":0,"walks":2,"strikeouts":4,"hitBatters":0,"win":false,"loss":false,"save":false,"completeGame":false}},{"playerId":"saark001","playerName":"Kirk Saarloos","gameId":"SLN200305260","date":"2003-05-26T00:00:00.000Z","points":"11.75","stats":{"inningsPitched":"3.0","hitsAllowed":1,"runsAllowed":0,"earnedRuns":0,"walks":2,"strikeouts":4,"hitBatters":0,"win":false,"loss":false,"save":false,"completeGame":false}},{"playerId":"germf001","playerName":"Franklyn Germán","gameId":"DET200305260","date":"2003-05-26T00:00:00.000Z","points":"9.25","stats":{"inningsPitched":"1.0","hitsAllowed":0,"runsAllowed":0,"earnedRuns":0,"walks":0,"strikeouts":1,"hitBatters":0,"win":false,"loss":false,"save":true,"completeGame":false}}]}