{"date":"1987-05-24","batting":[{"playerId":"thomr003","playerName":"Robby Thompson","gameId":"PHI198705240","date":"1987-05-24T00:00:00.000Z","points":"29.00","stats":{"atBats":4,"hits":3,"doubles":0,"triples":0,"homeRuns":1,"runs":1,"rbi":3,"walks":0,"stolenBases":1,"hitByPitch":0}},{"playerId":"bonib001","playerName":"Bobby Bonilla","gameId":"CIN198705240","date":"1987-05-24T00:00:00.000Z","points":"28.00","stats":{"atBats":4,"hits":2,"doubles":0,"triples":0,"homeRuns":2,"runs":2,"rbi":2,"walks":0,"stolenBases":0,"hitByPitch":0}},{"playerId":"clarj001","playerName":"Jack Clark","gameId":"HOU198705240","date":"1987-05-24T00:00:00.000Z","points":"28.00","stats":{"atBats":2,"hits":1,"doubles":0,"triples":0,"homeRuns":1,"runs":2,"rbi":4,"walks":3,"stolenBases":0,"hitByPitch":0}},{"playerId":"dyksl001","playerName":"Lenny Dykstra","gameId":"NYN198705240","date":"1987-05-24T00:00:00.000Z","points":"26.00","stats":{"atBats":4,"hits":2,"doubles":1,"triples":1,"homeRuns":0,"runs":1,"rbi":2,"walks":1,"stolenBases":1,"hitByPitch":0}},{"playerId":"joynw001","playerName":"Wally Joyner","gameId":"CAL198705240","date":"1987-05-24T00:00:00.000Z","points":"26.00","stats":{"atBats":5,"hits":3,"doubles":1,"triples":0,"homeRuns":1,"runs":2,"rbi":2,"walks":0,"stolenBases":0,"hitByPitch":0}},{"playerId":"cangj001","playerName":"John Cangelosi","gameId":"CIN198705240","date":"1987-05-24T00:00:00.000Z","points":"23.00","stats":{"atBats":2,"hits":0,"doubles":0,"triples":0,"homeRuns":0,"runs":1,"rbi":0,"walks":2,"stolenBases":3,"hitByPitch":1}},{"playerId":"tartd001","playerName":"Danny Tartabull","gameId":"TEX198705240","date":"1987-05-24T00:00:00.000Z","points":"22.00","stats":{"atBats":5,"hits":3,"doubles":0,"triples":0,"homeRuns":1,"runs":1,"rbi":2,"walks":0,"stolenBases":0,"hitByPitch":0}},{"playerId":"hrbek001","playerName":"Kent Hrbek","gameId":"MIN198705240","date":"1987-05-24T00:00:00.000Z","points":"21.00","stats":{"atBats":3,"hits":2,"doubles":0,"triples":0,"homeRuns":1,"runs":2,"rbi":1,"walks":1,"stolenBases":0,"hitByPitch":0}},{"playerId":"dauld001","playerName":"Darren Daulton","gameId":"PHI198705240","date":"1987-05-24T00:00:00.000Z","points":"20.00","stats":{"atBats":3,"hits":1,"doubles":0,"triples":0,"homeRuns":1,"runs":1,"rbi":3,"walks":1,"stolenBases":0,"hitByPitch":0}},{"playerId":"shelj001","playerName":"John Shelby","gameId":"NYN198705240","date":"1987-05-24T00:00:00.000Z","points":"20.00","stats":{"atBats":5,"hits":3,"doubles":1,"triples":0,"homeRuns":0,"runs":0,"rbi":2,"walks":0,"stolenBases":1,"hitByPitch":0}}],"pitching":[{"playerId":"langm001","playerName":"Mark Langston","gameId":"SEA198705240","date":"1987-05-24T00:00:00.000Z","points":"47.25","stats":{"inningsPitched":"9.0","hitsAllowed":4,"runsAllowed":2,"earnedRuns":2,"walks":3,"strikeouts":14,"hitBatters":0,"win":true,"loss":false,"save":false,"completeGame":true}},{"playerId":"robij002","playerName":"Jeff Robinson","gameId":"MIN198705240","date":"1987-05-24T00:00:00.000Z","points":"31.00","stats":{"inningsPitched":"8.0","hitsAllowed":5,"runsAllowed":2,"earnedRuns":1,"walks":3,"strikeouts":9,"hitBatters":0,"win":true,"loss":false,"save":false,"completeGame":false}},{"playerId":"fishb001","playerName":"Brian Fisher","gameId":"CIN198705240","date":"1987-05-24T00:00:00.000Z","points":"29.25","stats":{"inningsPitched":"9.0","hitsAllowed":5,"runsAllowed":2,"earnedRuns":2,"walks":2,"strikeouts":5,"hitBatters":0,"win":true,"loss":false,"save":false,"completeGame":true}},{"playerId":"magrj001","playerName":"Joe Magrane","gameId":"HOU198705240","date":"1987-05-24T00:00:00.000Z","points":"27.25","stats":{"inningsPitched":"9.0","hitsAllowed":7,"runsAllowed":2,"earnedRuns":2,"walks":2,"strikeouts":5,"hitBatters":0,"win":true,"loss":false,"save":false,"completeGame":true}},{"playerId":"youmf001","playerName":"Floyd Youmans","gameId":"SDN198705240","date":"1987-05-24T00:00:00.000Z","points":"23.50","stats":{"inningsPitched":"6.0","hitsAllowed":2,"runsAllowed":1,"earnedRuns":1,"walks":3,"strikeouts":6,"hitBatters":0,"win":true,"loss":false,"save":false,"completeGame":false}},{"playerId":"sutcr001","playerName":"Rick Sutcliffe","gameId":"CHN198705240","date":"1987-05-24T00:00:00.000Z","points":"23.00","stats":{"inningsPitched":"8.0","hitsAllowed":4,"runsAllowed":1,"earnedRuns":1,"walks":3,"strikeouts":7,"hitBatters":0,"win":false,"loss":false,"save":false,"completeGame":false}},{"playerId":"higut001","playerName":"Teddy Higuera","gameId":"MIL198705240","date":"1987-05-24T00:00:00.000Z","points":"22.25","stats":{"inningsPitched":"9.0","hitsAllowed":7,"runsAllowed":5,"earnedRuns":5,"walks":2,"strikeouts":9,"hitBatters":0,"win":false,"loss":true,"save":false,"completeGame":true}},{"playerId":"younc001","playerName":"Curt Young","gameId":"OAK198705240","date":"1987-05-24T00:00:00.000Z","points":"20.25","stats":{"inningsPitched":"9.0","hitsAllowed":6,"runsAllowed":4,"earnedRuns":3,"walks":1,"strikeouts":5,"hitBatters":0,"win":false,"loss":true,"save":false,"completeGame":true}},{"playerId":"pulec001","playerName":"Charlie Puleo","gameId":"CHN198705240","date":"1987-05-24T00:00:00.000Z","points":"18.50","stats":{"inningsPitched":"7.1","hitsAllowed":4,"runsAllowed":2,"earnedRuns":2,"walks":2,"strikeouts":6,"hitBatters":0,"win":false,"loss":false,"save":false,"completeGame":false}},{"playerId":"showe001","playerName":"Eric Show","gameId":"SDN198705240","date":"1987-05-24T00:00:00.000Z","points":"18.00","stats":{"inningsPitched":"8.0","hitsAllowed":3,"runsAllowed":2,"earnedRuns":1,"walks":3,"strikeouts":5,"hitBatters":0,"win":false,"loss":true,"save":false,"completeGame":false}}]}