{"date":"2023-08-07","batting":[{"playerId":"alonp001","playerName":"Pete Alonso","gameId":"NYN202308070","date":"2023-08-07T00:00:00.000Z","points":"41.00","stats":{"atBats":4,"hits":3,"doubles":0,"triples":0,"homeRuns":2,"runs":2,"rbi":6,"walks":0,"stolenBases":0,"hitByPitch":1}},{"playerId":"campl002","playerName":"Luis Campusano","gameId":"SDN202308070","date":"2023-08-07T00:00:00.000Z","points":"38.00","stats":{"atBats":4,"hits":4,"doubles":0,"triples":0,"homeRuns":2,"runs":2,"rbi":4,"walks":0,"stolenBases":0,"hitByPitch":0}},{"playerId":"reyep001","playerName":"Pablo Reyes","gameId":"BOS202308070","date":"2023-08-07T00:00:00.000Z","points":"37.00","stats":{"atBats":4,"hits":3,"doubles":1,"triples":0,"homeRuns":1,"runs":3,"rbi":4,"walks":0,"stolenBases":1,"hitByPitch":0}},{"playerId":"frels001","playerName":"Sal Frelick","gameId":"MIL202308070","date":"2023-08-07T00:00:00.000Z","points":"33.00","stats":{"atBats":3,"hits":2,"doubles":1,"triples":0,"homeRuns":1,"runs":3,"rbi":4,"walks":1,"stolenBases":0,"hitByPitch":1}},{"playerId":"corrc001","playerName":"Carlos Correa","gameId":"DET202308070","date":"2023-08-07T00:00:00.000Z","points":"27.00","stats":{"atBats":3,"hits":2,"doubles":1,"triples":0,"homeRuns":1,"runs":2,"rbi":4,"walks":0,"stolenBases":0,"hitByPitch":0}},{"playerId":"mendd002","playerName":"Danny Mendick","gameId":"NYN202308070","date":"2023-08-07T00:00:00.000Z","points":"23.00","stats":{"atBats":4,"hits":2,"doubles":0,"triples":0,"homeRuns":1,"runs":2,"rbi":3,"walks":0,"stolenBases":0,"hitByPitch":0}},{"playerId":"turab002","playerName":"Brice Turang","gameId":"MIL202308070","date":"2023-08-07T00:00:00.000Z","points":"23.00","stats":{"atBats":3,"hits":1,"doubles":0,"triples":0,"homeRuns":1,"runs":1,"rbi":2,"walks":1,"stolenBases":1,"hitByPitch":0}},{"playerId":"friet001","playerName":"TJ Friedl","gameId":"CIN202308070","date":"2023-08-07T00:00:00.000Z","points":"22.00","stats":{"atBats":4,"hits":2,"doubles":0,"triples":1,"homeRuns":0,"runs":1,"rbi":2,"walks":0,"stolenBases":1,"hitByPitch":0}},{"playerId":"davij006","playerName":"J. D. Davis","gameId":"ANA202308070","date":"2023-08-07T00:00:00.000Z","points":"21.00","stats":{"atBats":4,"hits":2,"doubles":0,"triples":0,"homeRuns":1,"runs":2,"rbi":1,"walks":1,"stolenBases":0,"hitByPitch":0}},{"playerId":"taylt002","playerName":"Tyrone Taylor","gameId":"MIL202308070","date":"2023-08-07T00:00:00.000Z","points":"21.00","stats":{"atBats":4,"hits":2,"doubles":0,"triples":0,"homeRuns":1,"runs":2,"rbi":2,"walks":0,"stolenBases":0,"hitByPitch":0}}],"pitching":[{"playerId":"peraf001","playerName":"Freddy Peralta","gameId":"MIL202308070","date":"2023-08-07T00:00:00.000Z","points":"43.75","stats":{"inningsPitched":"7.0","hitsAllowed":1,"runsAllowed":1,"earnedRuns":1,"walks":0,"strikeouts":13,"hitBatters":0,"win":true,"loss":false,"save":false,"completeGame":false}},{"playerId":"willg004","playerName":"Gavin Williams","gameId":"CLE202308070","date":"2023-08-07T00:00:00.000Z","points":"36.75","stats":{"inningsPitched":"7.0","hitsAllowed":1,"runsAllowed":0,"earnedRuns":0,"walks":1,"strikeouts":12,"hitBatters":1,"win":false,"loss":false,"save":false,"completeGame":false}},{"playerId":"willb003","playerName":"Brandon Williamson","gameId":"CIN202308070","date":"2023-08-07T00:00:00.000Z","points":"33.00","stats":{"inningsPitched":"6.2","hitsAllowed":3,"runsAllowed":1,"earnedRuns":1,"walks":0,"strikeouts":9,"hitBatters":0,"win":true,"loss":false,"save":false,"completeGame":false}},{"playerId":"lopep002","playerName":"Pablo López","gameId":"DET202308070","date":"2023-08-07T00:00:00.000Z","points":"31.75","stats":{"inningsPitched":"7.0","hitsAllowed":5,"runsAllowed":0,"earnedRuns":0,"walks":0,"strikeouts":8,"hitBatters":0,"win":true,"loss":false,"save":false,"completeGame":false}},{"playerId":"ragac001","playerName":"Cole Ragans","gameId":"BOS202308070","date":"2023-08-07T00:00:00.000Z","points":"30.00","stats":{"inningsPitched":"6.2","hitsAllowed":4,"runsAllowed":2,"earnedRuns":1,"walks":1,"strikeouts":11,"hitBatters":0,"win":false,"loss":false,"save":false,"completeGame":false}},{"playerId":"sandp002","playerName":"Patrick Sandoval","gameId":"ANA202308070","date":"2023-08-07T00:00:00.000Z","points":"21.00","stats":{"inningsPitched":"6.2","hitsAllowed":5,"runsAllowed":2,"earnedRuns":2,"walks":1,"strikeouts":8,"hitBatters":0,"win":false,"loss":false,"save":false,"completeGame":false}},{"playerId":"ceasd001","playerName":"Dylan Cease","gameId":"CHA202308070","date":"2023-08-07T00:00:00.000Z","points":"21.00","stats":{"inningsPitched":"5.1","hitsAllowed":1,"runsAllowed":0,"earnedRuns":0,"walks":7,"strikeouts":6,"hitBatters":0,"win":true,"loss":false,"save":false,"completeGame":false}},{"playerId":"sengk001","playerName":"Kodai Senga","gameId":"NYN202308070","date":"2023-08-07T00:00:00.000Z","points":"17.50","stats":{"inningsPitched":"6.0","hitsAllowed":7,"runsAllowed":2,"earnedRuns":2,"walks":2,"strikeouts":6,"hitBatters":0,"win":true,"loss":false,"save":false,"completeGame":false}},{"playerId":"shawb001","playerName":"Bryan Shaw","gameId":"CHA202308070","date":"2023-08-07T00:00:00.000Z","points":"16.50","stats":{"inningsPitched":"2.0","hitsAllowed":1,"runsAllowed":0,"earnedRuns":0,"walks":0,"strikeouts":4,"hitBatters":0,"win":false,"loss":false,"save":true,"completeGame":false}},{"playerId":"waldk003","playerName":"Ken Waldichuk","gameId":"OAK202308070","date":"2023-08-07T00:00:00.000Z","points":"16.50","stats":{"inningsPitched":"6.0","hitsAllowed":6,"runsAllowed":2,"earnedRuns":2,"walks":1,"strikeouts":7,"hitBatters":0,"win":false,"loss":false,"save":false,"completeGame":false}}]}